{
    "quotes": [
      {"day": 1, "quote": "The only way to do great work is to love what you do.", "author": "Steve Jobs"},
      {"day": 2, "quote": "Success is not how high you have climbed, but how you make a positive difference to the world.", "author": "Roy T. Bennett"},
      {"day": 3, "quote": "Believe you can and you're halfway there.", "author": "Theodore Roosevelt"},
      {"day": 4, "quote": "Don't watch the clock; do what it does. Keep going.", "author": "Sam Levenson"},
      {"day": 5, "quote": "You are never too old to set another goal or to dream a new dream.", "author": "C.S. Lewis"},
      {"day": 6, "quote": "The future belongs to those who believe in the beauty of their dreams.", "author": "Eleanor Roosevelt"},
      {"day": 7, "quote": "Act as if what you do makes a difference. It does.", "author": "William James"},
      {"day": 8, "quote": "Success usually comes to those who are too busy to be looking for it.", "author": "Henry David Thoreau"},
      {"day": 9, "quote": "Don’t be pushed around by the fears in your mind. Be led by the dreams in your heart.", "author": "Roy T. Bennett"},
      {"day": 10, "quote": "Opportunities don't happen. You create them.", "author": "Chris Grosser"},
      {"day": 11, "quote": "What you get by achieving your goals is not as important as what you become by achieving your goals.", "author": "Zig Ziglar"},
      {"day": 12, "quote": "You miss 100% of the shots you don’t take.", "author": "Wayne Gretzky"},
      {"day": 13, "quote": "The only limit to our realization of tomorrow will be our doubts of today.", "author": "Franklin D. Roosevelt"},
      {"day": 14, "quote": "It does not matter how slowly you go as long as you do not stop.", "author": "Confucius"},
      {"day": 15, "quote": "You have to expect things of yourself before you can do them.", "author": "John Steinbeck"},
      {"day": 16, "quote": "Limit your 'always' and your 'nevers'.", "author": "Amy Poehler"},
      {"day": 17, "quote": "The way to get started is to quit talking and begin doing.", "author": "Walt Disney"},
      {"day": 18, "quote": "Everything you’ve ever wanted is on the other side of fear.", "author": "George Addair"},
      {"day": 19, "quote": "Hardships often prepare ordinary people for an extraordinary destiny.", "author": "C.S. Lewis"},
      {"day": 20, "quote": "Believe in yourself and all that you are. Know that there is something inside you that is greater than any obstacle.", "author": "Christian D. Larson"},
      {"day": 21, "quote": "The only place where success comes before work is in the dictionary.", "author": "Vidal Sassoon"},
      {"day": 22, "quote": "Dream big and dare to fail.", "author": "Norman Vaughan"},
      {"day": 23, "quote": "Our greatest glory is not in never falling, but in rising every time we fall.", "author": "Confucius"},
      {"day": 24, "quote": "If you want to achieve greatness stop asking for permission.", "author": "Anonymous"},
      {"day": 25, "quote": "You can’t build a reputation on what you are going to do.", "author": "Henry Ford"},
      {"day": 26, "quote": "Success is not the key to happiness. Happiness is the key to success. If you love what you are doing, you will be successful.", "author": "Albert Schweitzer"},
      {"day": 27, "quote": "Dream it. Wish it. Do it.", "author": "Anonymous"},
      {"day": 28, "quote": "Success is walking from failure to failure with no loss of enthusiasm.", "author": "Winston S. Churchill"},
      {"day": 29, "quote": "The only way to achieve the impossible is to believe it is possible.", "author": "Charles Kingsleigh"},
      {"day": 30, "quote": "The harder you work for something, the greater you’ll feel when you achieve it.", "author": "Anonymous"},
      {"day": 31, "quote": "Dream bigger. Do bigger.", "author": "Anonymous"},
      {"day": 32, "quote": "Don't stop when you're tired. Stop when you're done.", "author": "Anonymous"},
      {"day": 33, "quote": "Wake up with determination. Go to bed with satisfaction.", "author": "Anonymous"},
      {"day": 34, "quote": "Push yourself, because no one else is going to do it for you.", "author": "Anonymous"},
      {"day": 35, "quote": "Great things never come from comfort zones.", "author": "Anonymous"},
      {"day": 36, "quote": "Dream it. Believe it. Build it.", "author": "Anonymous"},
      {"day": 37, "quote": "Success doesn’t just find you. You have to go out and get it.", "author": "Anonymous"},
      {"day": 38, "quote": "The harder you work for something, the greater you’ll feel when you achieve it.", "author": "Anonymous"},
      {"day": 39, "quote": "Don’t wait for opportunity. Create it.", "author": "Anonymous"},
      {"day": 40, "quote": "Sometimes we’re tested not to show our weaknesses, but to discover our strengths.", "author": "Anonymous"},
      {"day": 41, "quote": "The key to success is to focus on goals, not obstacles.", "author": "Anonymous"},
      {"day": 42, "quote": "Dream it. Wish it. Do it.", "author": "Anonymous"},
      {"day": 43, "quote": "You don’t have to be great to start, but you have to start to be great.", "author": "Zig Ziglar"},
      {"day": 44, "quote": "Success is not in what you have, but who you are.", "author": "Bo Bennett"},
      {"day": 45, "quote": "The future depends on what you do today.", "author": "Mahatma Gandhi"},
      {"day": 46, "quote": "What lies behind us and what lies before us are tiny matters compared to what lies within us.", "author": "Ralph Waldo Emerson"},
      {"day": 47, "quote": "The best way to predict your future is to create it.", "author": "Peter Drucker"},
      {"day": 48, "quote": "You are braver than you believe, stronger than you seem, and smarter than you think.", "author": "A.A. Milne"},
      {"day": 49, "quote": "Dream as if you’ll live forever. Live as if you’ll die today.", "author": "James Dean"},
      {"day": 50, "quote": "It’s not whether you get knocked down, it’s whether you get up.", "author": "Vince Lombardi"},
      {"day": 51, "quote": "The only limit to our realization of tomorrow is our doubts of today.", "author": "Franklin D. Roosevelt"},
      {"day": 52, "quote": "Do what you can with all you have, wherever you are.", "author": "Theodore Roosevelt"},
      {"day": 53, "quote": "Success is not the result of spontaneous combustion. You must set yourself on fire.", "author": "Arnold H. Glasow"},
      {"day": 54, "quote": "The road to success and the road to failure are almost exactly the same.", "author": "Colin R. Davis"},
      {"day": 55, "quote": "If you are not willing to risk the usual, you will have to settle for the ordinary.", "author": "Jim Rohn"},
      {"day": 56, "quote": "The only thing standing between you and your goal is the story you keep telling yourself as to why you can’t achieve it.", "author": "Jordan Belfort"},
      {"day": 57, "quote": "You don’t have to be great to start, but you have to start to be great.", "author": "Zig Ziglar"},
      {"day": 58, "quote": "Success is how high you bounce when you hit bottom.", "author": "General George S. Patton"},
      {"day": 59, "quote": "I find that the harder I work, the more luck I seem to have.", "author": "Thomas Jefferson"},
      {"day": 60, "quote": "Success is not in what you have, but who you are.", "author": "Bo Bennett"},
      {"day": 61, "quote": "The best revenge is massive success.", "author": "Frank Sinatra"},
      {"day": 62, "quote": "Success usually comes to those who are too busy to be looking for it.", "author": "Henry David Thoreau"},
      {"day": 63, "quote": "The successful warrior is the average man, with laser-like focus.", "author": "Bruce Lee"},
      {"day": 64, "quote": "You may be disappointed if you fail, but you are doomed if you don’t try.", "author": "Beverly Sills"},
      {"day": 65, "quote": "Don't be afraid to give up the good to go for the great.", "author": "John D. Rockefeller"},
      {"day": 66, "quote": "If you really look closely, most overnight successes took a long time.", "author": "Steve Jobs"},
      {"day": 67, "quote": "The man who moves a mountain begins by carrying away small stones.", "author": "Confucius"},
      {"day": 68, "quote": "Success is not the key to happiness. Happiness is the key to success. If you love what you are doing, you will be successful.", "author": "Albert Schweitzer"},
      {"day": 69, "quote": "I am not a product of my circumstances. I am a product of my decisions.", "author": "Stephen R. Covey"},
      {"day": 70, "quote": "You cannot swim for new horizons until you have courage to lose sight of the shore.", "author": "William Faulkner"},
      {"day": 71, "quote": "What we fear doing most is usually what we most need to do.", "author": "Tim Ferriss"},
      {"day": 72, "quote": "The only person you are destined to become is the person you decide to be.", "author": "Ralph Waldo Emerson"},
      {"day": 73, "quote": "Success is a journey, not a destination. The doing is often more important than the outcome.", "author": "Arthur Ashe"},
      {"day": 74, "quote": "Your limitation—it's only your imagination.", "author": "Anonymous"},
      {"day": 75, "quote": "Push yourself, because no one else is going to do it for you.", "author": "Anonymous"},
      {"day": 76, "quote": "Great things never come from comfort zones.", "author": "Anonymous"},
      {"day": 77, "quote": "Dream it. Wish it. Do it.", "author": "Anonymous"},
      {"day": 78, "quote": "Success doesn’t just find you. You have to go out and get it.", "author": "Anonymous"},
      {"day": 79, "quote": "The harder you work for something, the greater you’ll feel when you achieve it.", "author": "Anonymous"},
      {"day": 80, "quote": "Don’t wait for opportunity. Create it.", "author": "Anonymous"},
      {"day": 81, "quote": "Sometimes we’re tested not to show our weaknesses, but to discover our strengths.", "author": "Anonymous"},
      {"day": 82, "quote": "The key to success is to focus on goals, not obstacles.", "author": "Anonymous"},
      {"day": 83, "quote": "Dream it. Wish it. Do it.", "author": "Anonymous"},
      {"day": 84, "quote": "You don’t have to be great to start, but you have to start to be great.", "author": "Zig Ziglar"},
      {"day": 85, "quote": "Success is not in what you have, but who you are.", "author": "Bo Bennett"},
      {"day": 86, "quote": "The future depends on what you do today.", "author": "Mahatma Gandhi"},
      {"day": 87, "quote": "What lies behind us and what lies before us are tiny matters compared to what lies within us.", "author": "Ralph Waldo Emerson"},
      {"day": 88, "quote": "The best way to predict your future is to create it.", "author": "Peter Drucker"},
      {"day": 89, "quote": "You are braver than you believe, stronger than you seem, and smarter than you think.", "author": "A.A. Milne"},
      {"day": 90, "quote": "Dream as if you’ll live forever. Live as if you’ll die today.", "author": "James Dean"},
      {"day": 91, "quote": "It’s not whether you get knocked down, it’s whether you get up.", "author": "Vince Lombardi"},
      {"day": 92, "quote": "The only limit to our realization of tomorrow is our doubts of today.", "author": "Franklin D. Roosevelt"},
      {"day": 93, "quote": "Do what you can with all you have, wherever you are.", "author": "Theodore Roosevelt"},
      {"day": 94, "quote": "Success is not the result of spontaneous combustion. You must set yourself on fire.", "author": "Arnold H. Glasow"},
      {"day": 95, "quote": "The road to success and the road to failure are almost exactly the same.", "author": "Colin R. Davis"},
      {"day": 96, "quote": "If you are not willing to risk the usual, you will have to settle for the ordinary.", "author": "Jim Rohn"},
      {"day": 97, "quote": "The only thing standing between you and your goal is the story you keep telling yourself as to why you can’t achieve it.", "author": "Jordan Belfort"},
      {"day": 98, "quote": "You don’t have to be great to start, but you have to start to be great.", "author": "Zig Ziglar"},
      {"day": 99, "quote": "Success is how high you bounce when you hit bottom.", "author": "General George S. Patton"},
      {"day": 100, "quote": "I find that the harder I work, the more luck I seem to have.", "author": "Thomas Jefferson"},
      {"day": 101, "quote": "Success is not in what you have, but who you are.", "author": "Bo Bennett"},
      {"day": 102, "quote": "The best revenge is massive success.", "author": "Frank Sinatra"},
      {"day": 103, "quote": "Success usually comes to those who are too busy to be looking for it.", "author": "Henry David Thoreau"},
      {"day": 104, "quote": "The successful warrior is the average man, with laser-like focus.", "author": "Bruce Lee"},
      {"day": 105, "quote": "You may be disappointed if you fail, but you are doomed if you don’t try.", "author": "Beverly Sills"},
      {"day": 106, "quote": "Don't be afraid to give up the good to go for the great.", "author": "John D. Rockefeller"},
      {"day": 107, "quote": "If you really look closely, most overnight successes took a long time.", "author": "Steve Jobs"},
      {"day": 108, "quote": "The man who moves a mountain begins by carrying away small stones.", "author": "Confucius"},
      {"day": 109, "quote": "Success is not the key to happiness. Happiness is the key to success. If you love what you are doing, you will be successful.", "author": "Albert Schweitzer"},
      {"day": 110, "quote": "I am not a product of my circumstances. I am a product of my decisions.", "author": "Stephen R. Covey"},
      {"day": 111, "quote": "You cannot swim for new horizons until you have courage to lose sight of the shore.", "author": "William Faulkner"},
      {"day": 112, "quote": "What we fear doing most is usually what we most need to do.", "author": "Tim Ferriss"},
      {"day": 113, "quote": "The only person you are destined to become is the person you decide to be.", "author": "Ralph Waldo Emerson"},
      {"day": 114, "quote": "Success is a journey, not a destination. The doing is often more important than the outcome.", "author": "Arthur Ashe"},
      {"day": 115, "quote": "Your limitation—it's only your imagination.", "author": "Anonymous"},
      {"day": 116, "quote": "Push yourself, because no one else is going to do it for you.", "author": "Anonymous"},
      {"day": 117, "quote": "Great things never come from comfort zones.", "author": "Anonymous"},
      {"day": 118, "quote": "Dream it. Wish it. Do it.", "author": "Anonymous"},
      {"day": 119, "quote": "Success doesn’t just find you. You have to go out and get it.", "author": "Anonymous"},
      {"day": 120, "quote": "The harder you work for something, the greater you’ll feel when you achieve it.", "author": "Anonymous"},
      {"day": 121, "quote": "Don’t wait for opportunity. Create it.", "author": "Anonymous"},
      {"day": 122, "quote": "Sometimes we’re tested not to show our weaknesses, but to discover our strengths.", "author": "Anonymous"},
      {"day": 123, "quote": "The key to success is to focus on goals, not obstacles.", "author": "Anonymous"},
      {"day": 124, "quote": "Dream it. Wish it. Do it.", "author": "Anonymous"},
      {"day": 125, "quote": "You don’t have to be great to start, but you have to start to be great.", "author": "Zig Ziglar"},
      {"day": 126, "quote": "Success is not in what you have, but who you are.", "author": "Bo Bennett"},
      {"day": 127, "quote": "The future depends on what you do today.", "author": "Mahatma Gandhi"},
      {"day": 128, "quote": "What lies behind us and what lies before us are tiny matters compared to what lies within us.", "author": "Ralph Waldo Emerson"},
      {"day": 129, "quote": "The best way to predict your future is to create it.", "author": "Peter Drucker"},
      {"day": 130, "quote": "You are braver than you believe, stronger than you seem, and smarter than you think.", "author": "A.A. Milne"},
      {"day": 131, "quote": "Dream as if you’ll live forever. Live as if you’ll die today.", "author": "James Dean"},
      {"day": 132, "quote": "It’s not whether you get knocked down, it’s whether you get up.", "author": "Vince Lombardi"},
      {"day": 133, "quote": "The only limit to our realization of tomorrow is our doubts of today.", "author": "Franklin D. Roosevelt"},
      {"day": 134, "quote": "Do what you can with all you have, wherever you are.", "author": "Theodore Roosevelt"},
      {"day": 135, "quote": "Success is not the result of spontaneous combustion. You must set yourself on fire.", "author": "Arnold H. Glasow"},
      {"day": 136, "quote": "The road to success and the road to failure are almost exactly the same.", "author": "Colin R. Davis"},
      {"day": 137, "quote": "If you are not willing to risk the usual, you will have to settle for the ordinary.", "author": "Jim Rohn"},
      {"day": 138, "quote": "The only thing standing between you and your goal is the story you keep telling yourself as to why you can’t achieve it.", "author": "Jordan Belfort"},
      {"day": 139, "quote": "You don’t have to be great to start, but you have to start to be great.", "author": "Zig Ziglar"},
      {"day": 140, "quote": "Success is how high you bounce when you hit bottom.", "author": "General George S. Patton"},
      {"day": 141, "quote": "I find that the harder I work, the more luck I seem to have.", "author": "Thomas Jefferson"},
      {"day": 142, "quote": "Success is not in what you have, but who you are.", "author": "Bo Bennett"},
      {"day": 143, "quote": "The best revenge is massive success.", "author": "Frank Sinatra"},
      {"day": 144, "quote": "Success usually comes to those who are too busy to be looking for it.", "author": "Henry David Thoreau"},
      {"day": 145, "quote": "The successful warrior is the average man, with laser-like focus.", "author": "Bruce Lee"},
      {"day": 146, "quote": "You may be disappointed if you fail, but you are doomed if you don’t try.", "author": "Beverly Sills"},
      {"day": 147, "quote": "Don't be afraid to give up the good to go for the great.", "author": "John D. Rockefeller"},
      {"day": 148, "quote": "If you really look closely, most overnight successes took a long time.", "author": "Steve Jobs"},
      {"day": 149, "quote": "The man who moves a mountain begins by carrying away small stones.", "author": "Confucius"},
      {"day": 150, "quote": "Success is not the key to happiness. Happiness is the key to success. If you love what you are doing, you will be successful.", "author": "Albert Schweitzer"},
      {"day": 151, "quote": "I am not a product of my circumstances. I am a product of my decisions.", "author": "Stephen R. Covey"},
      {"day": 152, "quote": "You cannot swim for new horizons until you have courage to lose sight of the shore.", "author": "William Faulkner"},
      {"day": 153, "quote": "What we fear doing most is usually what we most need to do.", "author": "Tim Ferriss"},
      {"day": 154, "quote": "The only person you are destined to become is the person you decide to be.", "author": "Ralph Waldo Emerson"},
      {"day": 155, "quote": "Success is a journey, not a destination. The doing is often more important than the outcome.", "author": "Arthur Ashe"},
      {"day": 156, "quote": "Your limitation—it's only your imagination.", "author": "Anonymous"},
      {"day": 157, "quote": "Push yourself, because no one else is going to do it for you.", "author": "Anonymous"},
      {"day": 158, "quote": "Great things never come from comfort zones.", "author": "Anonymous"},
      {"day": 159, "quote": "Dream it. Wish it. Do it.", "author": "Anonymous"},
      {"day": 160, "quote": "Success doesn’t just find you. You have to go out and get it.", "author": "Anonymous"},
      {"day": 161, "quote": "The harder you work for something, the greater you’ll feel when you achieve it.", "author": "Anonymous"},
      {"day": 162, "quote": "Don’t wait for opportunity. Create it.", "author": "Anonymous"},
      {"day": 163, "quote": "Sometimes we’re tested not to show our weaknesses, but to discover our strengths.", "author": "Anonymous"},
      {"day": 164, "quote": "The key to success is to focus on goals, not obstacles.", "author": "Anonymous"},
      {"day": 165, "quote": "Dream it. Wish it. Do it.", "author": "Anonymous"},
      {"day": 166, "quote": "You don’t have to be great to start, but you have to start to be great.", "author": "Zig Ziglar"},
      {"day": 167, "quote": "Success is not in what you have, but who you are.", "author": "Bo Bennett"},
      {"day": 168, "quote": "The future depends on what you do today.", "author": "Mahatma Gandhi"},
      {"day": 169, "quote": "What lies behind us and what lies before us are tiny matters compared to what lies within us.", "author": "Ralph Waldo Emerson"},
      {"day": 170, "quote": "The best way to predict your future is to create it.", "author": "Peter Drucker"},
      {"day": 171, "quote": "You are braver than you believe, stronger than you seem, and smarter than you think.", "author": "A.A. Milne"},
      {"day": 172, "quote": "Dream as if you’ll live forever. Live as if you’ll die today.", "author": "James Dean"},
      {"day": 173, "quote": "It’s not whether you get knocked down, it’s whether you get up.", "author": "Vince Lombardi"},
      {"day": 174, "quote": "The only limit to our realization of tomorrow is our doubts of today.", "author": "Franklin D. Roosevelt"},
      {"day": 175, "quote": "Do what you can with all you have, wherever you are.", "author": "Theodore Roosevelt"},
      {"day": 176, "quote": "Success is not the result of spontaneous combustion. You must set yourself on fire.", "author": "Arnold H. Glasow"},
      {"day": 177, "quote": "The road to success and the road to failure are almost exactly the same.", "author": "Colin R. Davis"},
      {"day": 178, "quote": "If you are not willing to risk the usual, you will have to settle for the ordinary.", "author": "Jim Rohn"},
      {"day": 179, "quote": "The only thing standing between you and your goal is the story you keep telling yourself as to why you can’t achieve it.", "author": "Jordan Belfort"},
      {"day": 180, "quote": "You don’t have to be great to start, but you have to start to be great.", "author": "Zig Ziglar"},
      {"day": 181, "quote": "Success is how high you bounce when you hit bottom.", "author": "General George S. Patton"},
      {"day": 182, "quote": "I find that the harder I work, the more luck I seem to have.", "author": "Thomas Jefferson"},
      {"day": 183, "quote": "Success is not in what you have, but who you are.", "author": "Bo Bennett"},
      {"day": 184, "quote": "The best revenge is massive success.", "author": "Frank Sinatra"},
      {"day": 185, "quote": "Success usually comes to those who are too busy to be looking for it.", "author": "Henry David Thoreau"},
      {"day": 186, "quote": "The successful warrior is the average man, with laser-like focus.", "author": "Bruce Lee"},
      {"day": 187, "quote": "You may be disappointed if you fail, but you are doomed if you don’t try.", "author": "Beverly Sills"},
      {"day": 188, "quote": "Don't be afraid to give up the good to go for the great.", "author": "John D. Rockefeller"},
      {"day": 189, "quote": "If you really look closely, most overnight successes took a long time.", "author": "Steve Jobs"},
      {"day": 190, "quote": "The man who moves a mountain begins by carrying away small stones.", "author": "Confucius"},
      {"day": 191, "quote": "Success is not the key to happiness. Happiness is the key to success. If you love what you are doing, you will be successful.", "author": "Albert Schweitzer"},
      {"day": 192, "quote": "I am not a product of my circumstances. I am a product of my decisions.", "author": "Stephen R. Covey"},
      {"day": 193, "quote": "You cannot swim for new horizons until you have courage to lose sight of the shore.", "author": "William Faulkner"},
      {"day": 194, "quote": "What we fear doing most is usually what we most need to do.", "author": "Tim Ferriss"},
      {"day": 195, "quote": "The only person you are destined to become is the person you decide to be.", "author": "Ralph Waldo Emerson"},
      {"day": 196, "quote": "Success is a journey, not a destination. The doing is often more important than the outcome.", "author": "Arthur Ashe"},
      {"day": 197, "quote": "Your limitation—it's only your imagination.", "author": "Anonymous"},
      {"day": 198, "quote": "Push yourself, because no one else is going to do it for you.", "author": "Anonymous"},
      {"day": 199, "quote": "Great things never come from comfort zones.", "author": "Anonymous"},
      {"day": 200, "quote": "Dream it. Wish it. Do it.", "author": "Anonymous"},
      {"day": 201, "quote": "Success doesn’t just find you. You have to go out and get it.", "author": "Anonymous"},
      {"day": 202, "quote": "The harder you work for something, the greater you’ll feel when you achieve it.", "author": "Anonymous"},
      {"day": 203, "quote": "Don’t wait for opportunity. Create it.", "author": "Anonymous"},
      {"day": 204, "quote": "Sometimes we’re tested not to show our weaknesses, but to discover our strengths.", "author": "Anonymous"},
      {"day": 205, "quote": "The key to success is to focus on goals, not obstacles.", "author": "Anonymous"},
      {"day": 206, "quote": "Dream it. Wish it. Do it.", "author": "Anonymous"},
      {"day": 207, "quote": "You don’t have to be great to start, but you have to start to be great.", "author": "Zig Ziglar"},
      {"day": 208, "quote": "Success is not in what you have, but who you are.", "author": "Bo Bennett"},
      {"day": 209, "quote": "The future depends on what you do today.", "author": "Mahatma Gandhi"},
      {"day": 210, "quote": "What lies behind us and what lies before us are tiny matters compared to what lies within us.", "author": "Ralph Waldo Emerson"},
      {"day": 211, "quote": "The best way to predict your future is to create it.", "author": "Peter Drucker"},
      {"day": 212, "quote": "You are braver than you believe, stronger than you seem, and smarter than you think.", "author": "A.A. Milne"},
      {"day": 213, "quote": "Dream as if you’ll live forever. Live as if you’ll die today.", "author": "James Dean"},
      {"day": 214, "quote": "It’s not whether you get knocked down, it’s whether you get up.", "author": "Vince Lombardi"},
      {"day": 215, "quote": "The only limit to our realization of tomorrow is our doubts of today.", "author": "Franklin D. Roosevelt"},
      {"day": 216, "quote": "Do what you can with all you have, wherever you are.", "author": "Theodore Roosevelt"},
      {"day": 217, "quote": "Success is not the result of spontaneous combustion. You must set yourself on fire.", "author": "Arnold H. Glasow"},
      {"day": 218, "quote": "The road to success and the road to failure are almost exactly the same.", "author": "Colin R. Davis"},
      {"day": 219, "quote": "If you are not willing to risk the usual, you will have to settle for the ordinary.", "author": "Jim Rohn"},
      {"day": 220, "quote": "The only thing standing between you and your goal is the story you keep telling yourself as to why you can’t achieve it.", "author": "Jordan Belfort"},
      {"day": 221, "quote": "You don’t have to be great to start, but you have to start to be great.", "author": "Zig Ziglar"},
      {"day": 222, "quote": "Success is how high you bounce when you hit bottom.", "author": "General George S. Patton"},
      {"day": 223, "quote": "I find that the harder I work, the more luck I seem to have.", "author": "Thomas Jefferson"},
      {"day": 224, "quote": "Success is not in what you have, but who you are.", "author": "Bo Bennett"},
      {"day": 225, "quote": "The best revenge is massive success.", "author": "Frank Sinatra"},
      {"day": 226, "quote": "Success usually comes to those who are too busy to be looking for it.", "author": "Henry David Thoreau"},
      {"day": 227, "quote": "The successful warrior is the average man, with laser-like focus.", "author": "Bruce Lee"},
      {"day": 228, "quote": "You may be disappointed if you fail, but you are doomed if you don’t try.", "author": "Beverly Sills"},
      {"day": 229, "quote": "Don't be afraid to give up the good to go for the great.", "author": "John D. Rockefeller"},
      {"day": 230, "quote": "If you really look closely, most overnight successes took a long time.", "author": "Steve Jobs"},
      {"day": 231, "quote": "The man who moves a mountain begins by carrying away small stones.", "author": "Confucius"},
      {"day": 232, "quote": "Success is not the key to happiness. Happiness is the key to success. If you love what you are doing, you will be successful.", "author": "Albert Schweitzer"},
      {"day": 233, "quote": "I am not a product of my circumstances. I am a product of my decisions.", "author": "Stephen R. Covey"},
      {"day": 234, "quote": "You cannot swim for new horizons until you have courage to lose sight of the shore.", "author": "William Faulkner"},
      {"day": 235, "quote": "What we fear doing most is usually what we most need to do.", "author": "Tim Ferriss"},
      {"day": 236, "quote": "The only person you are destined to become is the person you decide to be.", "author": "Ralph Waldo Emerson"},
      {"day": 237, "quote": "Success is a journey, not a destination. The doing is often more important than the outcome.", "author": "Arthur Ashe"},
      {"day": 238, "quote": "Your limitation—it's only your imagination.", "author": "Anonymous"},
      {"day": 239, "quote": "Push yourself, because no one else is going to do it for you.", "author": "Anonymous"},
      {"day": 240, "quote": "Great things never come from comfort zones.", "author": "Anonymous"},
      {"day": 241, "quote": "Dream it. Wish it. Do it.", "author": "Anonymous"},
      {"day": 242, "quote": "Success doesn’t just find you. You have to go out and get it.", "author": "Anonymous"},
      {"day": 243, "quote": "The harder you work for something, the greater you’ll feel when you achieve it.", "author": "Anonymous"},
      {"day": 244, "quote": "Don’t wait for opportunity. Create it.", "author": "Anonymous"},
      {"day": 245, "quote": "Sometimes we’re tested not to show our weaknesses, but to discover our strengths.", "author": "Anonymous"},
      {"day": 246, "quote": "The key to success is to focus on goals, not obstacles.", "author": "Anonymous"},
      {"day": 247, "quote": "Dream it. Wish it. Do it.", "author": "Anonymous"},
      {"day": 248, "quote": "You don’t have to be great to start, but you have to start to be great.", "author": "Zig Ziglar"},
      {"day": 249, "quote": "Success is not in what you have, but who you are.", "author": "Bo Bennett"},
      {"day": 250, "quote": "The future depends on what you do today.", "author": "Mahatma Gandhi"},
      {"day": 251, "quote": "What lies behind us and what lies before us are tiny matters compared to what lies within us.", "author": "Ralph Waldo Emerson"},
      {"day": 252, "quote": "The best way to predict your future is to create it.", "author": "Peter Drucker"},
      {"day": 253, "quote": "You are braver than you believe, stronger than you seem, and smarter than you think.", "author": "A.A. Milne"},
      {"day": 254, "quote": "Dream as if you’ll live forever. Live as if you’ll die today.", "author": "James Dean"},
      {"day": 255, "quote": "It’s not whether you get knocked down, it’s whether you get up.", "author": "Vince Lombardi"},
      {"day": 256, "quote": "The only limit to our realization of tomorrow is our doubts of today.", "author": "Franklin D. Roosevelt"},
      {"day": 257, "quote": "Do what you can with all you have, wherever you are.", "author": "Theodore Roosevelt"},
      {"day": 258, "quote": "Success is not the result of spontaneous combustion. You must set yourself on fire.", "author": "Arnold H. Glasow"},
      {"day": 259, "quote": "The road to success and the road to failure are almost exactly the same.", "author": "Colin R. Davis"},
      {"day": 260, "quote": "If you are not willing to risk the usual, you will have to settle for the ordinary.", "author": "Jim Rohn"},
      {"day": 261, "quote": "The only thing standing between you and your goal is the story you keep telling yourself as to why you can’t achieve it.", "author": "Jordan Belfort"},
      {"day": 262, "quote": "You don’t have to be great to start, but you have to start to be great.", "author": "Zig Ziglar"},
      {"day": 263, "quote": "Success is how high you bounce when you hit bottom.", "author": "General George S. Patton"},
      {"day": 264, "quote": "I find that the harder I work, the more luck I seem to have.", "author": "Thomas Jefferson"},
      {"day": 265, "quote": "Success is not in what you have, but who you are.", "author": "Bo Bennett"},
      {"day": 266, "quote": "The best revenge is massive success.", "author": "Frank Sinatra"},
      {"day": 267, "quote": "Success usually comes to those who are too busy to be looking for it.", "author": "Henry David Thoreau"},
      {"day": 268, "quote": "The successful warrior is the average man, with laser-like focus.", "author": "Bruce Lee"},
      {"day": 269, "quote": "You may be disappointed if you fail, but you are doomed if you don’t try.", "author": "Beverly Sills"},
      {"day": 270, "quote": "Don't be afraid to give up the good to go for the great.", "author": "John D. Rockefeller"},
      {"day": 271, "quote": "If you really look closely, most overnight successes took a long time.", "author": "Steve Jobs"},
      {"day": 272, "quote": "The man who moves a mountain begins by carrying away small stones.", "author": "Confucius"},
      {"day": 273, "quote": "Success is not the key to happiness. Happiness is the key to success. If you love what you are doing, you will be successful.", "author": "Albert Schweitzer"},
      {"day": 274, "quote": "I am not a product of my circumstances. I am a product of my decisions.", "author": "Stephen R. Covey"},
      {"day": 275, "quote": "You cannot swim for new horizons until you have courage to lose sight of the shore.", "author": "William Faulkner"},
      {"day": 276, "quote": "What we fear doing most is usually what we most need to do.", "author": "Tim Ferriss"},
      {"day": 277, "quote": "The only person you are destined to become is the person you decide to be.", "author": "Ralph Waldo Emerson"},
      {"day": 278, "quote": "Success is a journey, not a destination. The doing is often more important than the outcome.", "author": "Arthur Ashe"},
      {"day": 279, "quote": "Your limitation—it's only your imagination.", "author": "Anonymous"},
      {"day": 280, "quote": "Push yourself, because no one else is going to do it for you.", "author": "Anonymous"},
      {"day": 281, "quote": "Great things never come from comfort zones.", "author": "Anonymous"},
      {"day": 282, "quote": "Dream it. Wish it. Do it.", "author": "Anonymous"},
      {"day": 283, "quote": "Success doesn’t just find you. You have to go out and get it.", "author": "Anonymous"},
      {"day": 284, "quote": "The harder you work for something, the greater you’ll feel when you achieve it.", "author": "Anonymous"},
      {"day": 285, "quote": "Don’t wait for opportunity. Create it.", "author": "Anonymous"},
      {"day": 286, "quote": "Sometimes we’re tested not to show our weaknesses, but to discover our strengths.", "author": "Anonymous"},
      {"day": 287, "quote": "The key to success is to focus on goals, not obstacles.", "author": "Anonymous"},
      {"day": 288, "quote": "Dream it. Wish it. Do it.", "author": "Anonymous"},
      {"day": 289, "quote": "You don’t have to be great to start, but you have to start to be great.", "author": "Zig Ziglar"},
      {"day": 290, "quote": "Success is not in what you have, but who you are.", "author": "Bo Bennett"},
      {"day": 291, "quote": "The future depends on what you do today.", "author": "Mahatma Gandhi"},
      {"day": 292, "quote": "What lies behind us and what lies before us are tiny matters compared to what lies within us.", "author": "Ralph Waldo Emerson"},
      {"day": 293, "quote": "The best way to predict your future is to create it.", "author": "Peter Drucker"},
      {"day": 294, "quote": "You are braver than you believe, stronger than you seem, and smarter than you think.", "author": "A.A. Milne"},
      {"day": 295, "quote": "Dream as if you’ll live forever. Live as if you’ll die today.", "author": "James Dean"},
      {"day": 296, "quote": "It’s not whether you get knocked down, it’s whether you get up.", "author": "Vince Lombardi"},
      {"day": 297, "quote": "The only limit to our realization of tomorrow is our doubts of today.", "author": "Franklin D. Roosevelt"},
      {"day": 298, "quote": "Do what you can with all you have, wherever you are.", "author": "Theodore Roosevelt"},
      {"day": 299, "quote": "Success is not the result of spontaneous combustion. You must set yourself on fire.", "author": "Arnold H. Glasow"},
      {"day": 300, "quote": "The road to success and the road to failure are almost exactly the same.", "author": "Colin R. Davis"},
      {"day": 301, "quote": "If you are not willing to risk the usual, you will have to settle for the ordinary.", "author": "Jim Rohn"},
      {"day": 302, "quote": "The only thing standing between you and your goal is the story you keep telling yourself as to why you can’t achieve it.", "author": "Jordan Belfort"},
      {"day": 303, "quote": "You don’t have to be great to start, but you have to start to be great.", "author": "Zig Ziglar"},
      {"day": 304, "quote": "Success is how high you bounce when you hit bottom.", "author": "General George S. Patton"},
      {"day": 305, "quote": "I find that the harder I work, the more luck I seem to have.", "author": "Thomas Jefferson"},
      {"day": 306, "quote": "Success is not in what you have, but who you are.", "author": "Bo Bennett"},
      {"day": 307, "quote": "The best revenge is massive success.", "author": "Frank Sinatra"},
      {"day": 308, "quote": "Success usually comes to those who are too busy to be looking for it.", "author": "Henry David Thoreau"},
      {"day": 309, "quote": "The successful warrior is the average man, with laser-like focus.", "author": "Bruce Lee"},
      {"day": 310, "quote": "You may be disappointed if you fail, but you are doomed if you don’t try.", "author": "Beverly Sills"},
      {"day": 311, "quote": "Don't be afraid to give up the good to go for the great.", "author": "John D. Rockefeller"},
      {"day": 312, "quote": "If you really look closely, most overnight successes took a long time.", "author": "Steve Jobs"},
      {"day": 313, "quote": "The man who moves a mountain begins by carrying away small stones.", "author": "Confucius"},
      {"day": 314, "quote": "Success is not the key to happiness. Happiness is the key to success. If you love what you are doing, you will be successful.", "author": "Albert Schweitzer"},
      {"day": 315, "quote": "I am not a product of my circumstances. I am a product of my decisions.", "author": "Stephen R. Covey"},
      {"day": 316, "quote": "You cannot swim for new horizons until you have courage to lose sight of the shore.", "author": "William Faulkner"},
      {"day": 317, "quote": "What we fear doing most is usually what we most need to do.", "author": "Tim Ferriss"},
      {"day": 318, "quote": "The only person you are destined to become is the person you decide to be.", "author": "Ralph Waldo Emerson"},
      {"day": 319, "quote": "Success is a journey, not a destination. The doing is often more important than the outcome.", "author": "Arthur Ashe"},
      {"day": 320, "quote": "Your limitation—it's only your imagination.", "author": "Anonymous"},
      {"day": 321, "quote": "Push yourself, because no one else is going to do it for you.", "author": "Anonymous"},
      {"day": 322, "quote": "Great things never come from comfort zones.", "author": "Anonymous"},
      {"day": 323, "quote": "Dream it. Wish it. Do it.", "author": "Anonymous"},
      {"day": 324, "quote": "Success doesn’t just find you. You have to go out and get it.", "author": "Anonymous"},
      {"day": 325, "quote": "The harder you work for something, the greater you’ll feel when you achieve it.", "author": "Anonymous"},
      {"day": 326, "quote": "Don’t wait for opportunity. Create it.", "author": "Anonymous"},
      {"day": 327, "quote": "Sometimes we’re tested not to show our weaknesses, but to discover our strengths.", "author": "Anonymous"},
      {"day": 328, "quote": "The key to success is to focus on goals, not obstacles.", "author": "Anonymous"},
      {"day": 329, "quote": "Dream it. Wish it. Do it.", "author": "Anonymous"},
      {"day": 330, "quote": "You don’t have to be great to start, but you have to start to be great.", "author": "Zig Ziglar"},
      {"day": 331, "quote": "Success is not in what you have, but who you are.", "author": "Bo Bennett"},
      {"day": 332, "quote": "The future depends on what you do today.", "author": "Mahatma Gandhi"},
      {"day": 333, "quote": "What lies behind us and what lies before us are tiny matters compared to what lies within us.", "author": "Ralph Waldo Emerson"},
      {"day": 334, "quote": "The best way to predict your future is to create it.", "author": "Peter Drucker"},
      {"day": 335, "quote": "You are braver than you believe, stronger than you seem, and smarter than you think.", "author": "A.A. Milne"},
      {"day": 336, "quote": "Dream as if you’ll live forever. Live as if you’ll die today.", "author": "James Dean"},
      {"day": 337, "quote": "It’s not whether you get knocked down, it’s whether you get up.", "author": "Vince Lombardi"},
      {"day": 338, "quote": "The only limit to our realization of tomorrow is our doubts of today.", "author": "Franklin D. Roosevelt"},
      {"day": 339, "quote": "Do what you can with all you have, wherever you are.", "author": "Theodore Roosevelt"},
      {"day": 340, "quote": "Success is not the result of spontaneous combustion. You must set yourself on fire.", "author": "Arnold H. Glasow"},
      {"day": 341, "quote": "The road to success and the road to failure are almost exactly the same.", "author": "Colin R. Davis"},
      {"day": 342, "quote": "If you are not willing to risk the usual, you will have to settle for the ordinary.", "author": "Jim Rohn"},
      {"day": 343, "quote": "The only thing standing between you and your goal is the story you keep telling yourself as to why you can’t achieve it.", "author": "Jordan Belfort"},
      {"day": 344, "quote": "You don’t have to be great to start, but you have to start to be great.", "author": "Zig Ziglar"},
      {"day": 345, "quote": "Success is how high you bounce when you hit bottom.", "author": "General George S. Patton"},
      {"day": 346, "quote": "I find that the harder I work, the more luck I seem to have.", "author": "Thomas Jefferson"},
      {"day": 347, "quote": "Success is not in what you have, but who you are.", "author": "Bo Bennett"},
      {"day": 348, "quote": "The best revenge is massive success.", "author": "Frank Sinatra"},
      {"day": 349, "quote": "Success usually comes to those who are too busy to be looking for it.", "author": "Henry David Thoreau"},
      {"day": 350, "quote": "The successful warrior is the average man, with laser-like focus.", "author": "Bruce Lee"},
      {"day": 351, "quote": "You may be disappointed if you fail, but you are doomed if you don’t try.", "author": "Beverly Sills"},
      {"day": 352, "quote": "Don't be afraid to give up the good to go for the great.", "author": "John D. Rockefeller"},
      {"day": 353, "quote": "If you really look closely, most overnight successes took a long time.", "author": "Steve Jobs"},
      {"day": 354, "quote": "The man who moves a mountain begins by carrying away small stones.", "author": "Confucius"},
      {"day": 355, "quote": "Success is not the key to happiness. Happiness is the key to success. If you love what you are doing, you will be successful.", "author": "Albert Schweitzer"},
      {"day": 356, "quote": "I am not a product of my circumstances. I am a product of my decisions.", "author": "Stephen R. Covey"},
      {"day": 357, "quote": "You cannot swim for new horizons until you have courage to lose sight of the shore.", "author": "William Faulkner"},
      {"day": 358, "quote": "What we fear doing most is usually what we most need to do.", "author": "Tim Ferriss"},
      {"day": 359, "quote": "The only person you are destined to become is the person you decide to be.", "author": "Ralph Waldo Emerson"},
      {"day": 360, "quote": "Success is a journey, not a destination. The doing is often more important than the outcome.", "author": "Arthur Ashe"},
      {"day": 361, "quote": "Your limitation—it's only your imagination.", "author": "Anonymous"},
      {"day": 362, "quote": "Push yourself, because no one else is going to do it for you.", "author": "Anonymous"},
      {"day": 363, "quote": "Great things never come from comfort zones.", "author": "Anonymous"},
      {"day": 364, "quote": "Dream it. Wish it. Do it.", "author": "Anonymous"},
      {"day": 365, "quote": "Success doesn’t just find you. You have to go out and get it.", "author": "Anonymous"}
    ]
  }